{
  "description": "项目配置文件",
  "packOptions": {
    "ignore": []
  },
  "setting": {
    "urlCheck": false,
    "es6": true,
    "postcss": true,
    "minified": true,
    "newFeature": true,
    "coverView": true,
    "nodeModules": true,
    "autoAudits": false,
    "scopeDataCheck": false,
    "checkInvalidKey": true,
    "checkSiteMap": true,
    "uploadWithSourceMap": true,
    "compileHotReLoad": false,
    "babelSetting": {
      "ignore": [],
      "disablePlugins": [],
      "outputPath": ""
    },
    "useIsolateContext": true,
    "useCompilerModule": true,
    "userConfirmedUseCompilerModuleSwitch": false,
    "userConfirmedBundleSwitch": false,
    "packNpmManually": false,
    "packNpmRelationList": [],
    "minifyWXSS": true,
    "useMultiFrameRuntime": false,
    "useApiHook": true,
    "bundle": false
  },
  "compileType": "miniprogram",
  "libVersion": "2.13.0",
  "appid": "wxad76ddecca495342",
  "projectname": "Love%20Animation",
  "debugOptions": {
    "hidedInDevtools": []
  },
  "isGameTourist": false,
  "simulatorType": "wechat",
  "simulatorPluginLibVersion": {},
  "condition": {
    "search": {
      "list": []
    },
    "conversation": {
      "list": []
    },
    "plugin": {
      "list": []
    },
    "game": {
      "currentL": -1,
      "list": []
    },
    "gamePlugin": {
      "list": []
    },
    "miniprogram": {
      "list": [
        {
          "id": -1,
          "name": "pages/home/home",
          "pathName": "pages/home/home",
          "query": "",
          "scene": null
        },
        {
          "id": -1,
          "name": "pages/picture/picture",
          "pathName": "pages/picture/picture",
          "query": "",
          "scene": null
        },
        {
          "id": -1,
          "name": "pages/demo/demo",
          "pathName": "pages/demo/demo",
          "scene": null
        }
      ]
    }
  }
}